{
  "vehicle": {
    "number": 25,
    "capacity": 1000
  },
  "customers": [
    {
      "id": 0,
      "x": 40,
      "y": 50,
      "demand": 0,
      "ready_time": 0,
      "due_time": 960,
      "service_time": 0
    },
    {
      "id": 1,
      "x": 25,
      "y": 85,
      "demand": 20,
      "ready_time": 591,
      "due_time": 874,
      "service_time": 10
    },
    {
      "id": 2,
      "x": 22,
      "y": 75,
      "demand": 30,
      "ready_time": 73,
      "due_time": 350,
      "service_time": 10
    },
    {
      "id": 3,
      "x": 22,
      "y": 85,
      "demand": 10,
      "ready_time": 473,
      "due_time": 588,
      "service_time": 10
    },
    {
      "id": 4,
      "x": 20,
      "y": 80,
      "demand": 40,
      "ready_time": 418,
      "due_time": 913,
      "service_time": 10
    },
    {
      "id": 5,
      "x": 20,
      "y": 85,
      "demand": 20,
      "ready_time": 40,
      "due_time": 390,
      "service_time": 10
    },
    {
      "id": 6,
      "x": 18,
      "y": 75,
      "demand": 20,
      "ready_time": 249,
      "due_time": 646,
      "service_time": 10
    },
    {
      "id": 7,
      "x": 15,
      "y": 75,
      "demand": 20,
      "ready_time": 281,
      "due_time": 438,
      "service_time": 10
    },
    {
      "id": 8,
      "x": 15,
      "y": 80,
      "demand": 10,
      "ready_time": 272,
      "due_time": 581,
      "service_time": 10
    },
    {
      "id": 9,
      "x": 10,
      "y": 35,
      "demand": 20,
      "ready_time": 236,
      "due_time": 625,
      "service_time": 10
    },
    {
      "id": 10,
      "x": 10,
      "y": 40,
      "demand": 30,
      "ready_time": 470,
      "due_time": 687,
      "service_time": 10
    },
    {
      "id": 11,
      "x": 8,
      "y": 40,
      "demand": 40,
      "ready_time": 33,
      "due_time": 510,
      "service_time": 10
    },
    {
      "id": 12,
      "x": 8,
      "y": 45,
      "demand": 20,
      "ready_time": 166,
      "due_time": 399,
      "service_time": 10
    },
    {
      "id": 13,
      "x": 5,
      "y": 35,
      "demand": 10,
      "ready_time": 359,
      "due_time": 911,
      "service_time": 10
    },
    {
      "id": 14,
      "x": 5,
      "y": 45,
      "demand": 10,
      "ready_time": 35,
      "due_time": 457,
      "service_time": 10
    },
    {
      "id": 15,
      "x": 2,
      "y": 40,
      "demand": 20,
      "ready_time": 39,
      "due_time": 538,
      "service_time": 10
    },
    {
      "id": 16,
      "x": 0,
      "y": 40,
      "demand": 20,
      "ready_time": 214,
      "due_time": 415,
      "service_time": 10
    },
    {
      "id": 17,
      "x": 0,
      "y": 45,
      "demand": 20,
      "ready_time": 359,
      "due_time": 909,
      "service_time": 10
    },
    {
      "id": 18,
      "x": 44,
      "y": 5,
      "demand": 20,
      "ready_time": 338,
      "due_time": 451,
      "service_time": 10
    },
    {
      "id": 19,
      "x": 42,
      "y": 10,
      "demand": 40,
      "ready_time": 205,
      "due_time": 422,
      "service_time": 10
    },
    {
      "id": 20,
      "x": 42,
      "y": 15,
      "demand": 10,
      "ready_time": 511,
      "due_time": 682,
      "service_time": 10
    },
    {
      "id": 21,
      "x": 40,
      "y": 5,
      "demand": 10,
      "ready_time": 158,
      "due_time": 391,
      "service_time": 10
    },
    {
      "id": 22,
      "x": 40,
      "y": 15,
      "demand": 40,
      "ready_time": 263,
      "due_time": 606,
      "service_time": 10
    },
    {
      "id": 23,
      "x": 38,
      "y": 5,
      "demand": 30,
      "ready_time": 45,
      "due_time": 522,
      "service_time": 10
    },
    {
      "id": 24,
      "x": 38,
      "y": 15,
      "demand": 10,
      "ready_time": 598,
      "due_time": 883,
      "service_time": 10
    },
    {
      "id": 25,
      "x": 35,
      "y": 5,
      "demand": 20,
      "ready_time": 348,
      "due_time": 904,
      "service_time": 10
    },
    {
      "id": 26,
      "x": 95,
      "y": 30,
      "demand": 30,
      "ready_time": 509,
      "due_time": 668,
      "service_time": 10
    },
    {
      "id": 27,
      "x": 95,
      "y": 35,
      "demand": 20,
      "ready_time": 57,
      "due_time": 664,
      "service_time": 10
    },
    {
      "id": 28,
      "x": 92,
      "y": 30,
      "demand": 10,
      "ready_time": 68,
      "due_time": 349,
      "service_time": 10
    },
    {
      "id": 29,
      "x": 90,
      "y": 35,
      "demand": 10,
      "ready_time": 131,
      "due_time": 376,
      "service_time": 10
    },
    {
      "id": 30,
      "x": 88,
      "y": 30,
      "demand": 10,
      "ready_time": 114,
      "due_time": 497,
      "service_time": 10
    },
    {
      "id": 31,
      "x": 88,
      "y": 35,
      "demand": 20,
      "ready_time": 102,
      "due_time": 347,
      "service_time": 10
    },
    {
      "id": 32,
      "x": 87,
      "y": 30,
      "demand": 10,
      "ready_time": 564,
      "due_time": 797,
      "service_time": 10
    },
    {
      "id": 33,
      "x": 85,
      "y": 25,
      "demand": 10,
      "ready_time": 51,
      "due_time": 673,
      "service_time": 10
    },
    {
      "id": 34,
      "x": 85,
      "y": 35,
      "demand": 30,
      "ready_time": 462,
      "due_time": 631,
      "service_time": 10
    },
    {
      "id": 35,
      "x": 67,
      "y": 85,
      "demand": 20,
      "ready_time": 396,
      "due_time": 905,
      "service_time": 10
    },
    {
      "id": 36,
      "x": 65,
      "y": 85,
      "demand": 40,
      "ready_time": 43,
      "due_time": 712,
      "service_time": 10
    },
    {
      "id": 37,
      "x": 65,
      "y": 82,
      "demand": 10,
      "ready_time": 530,
      "due_time": 703,
      "service_time": 10
    },
    {
      "id": 38,
      "x": 62,
      "y": 80,
      "demand": 30,
      "ready_time": 131,
      "due_time": 544,
      "service_time": 10
    },
    {
      "id": 39,
      "x": 60,
      "y": 80,
      "demand": 10,
      "ready_time": 36,
      "due_time": 800,
      "service_time": 10
    },
    {
      "id": 40,
      "x": 60,
      "y": 85,
      "demand": 30,
      "ready_time": 233,
      "due_time": 544,
      "service_time": 10
    },
    {
      "id": 41,
      "x": 58,
      "y": 75,
      "demand": 20,
      "ready_time": 207,
      "due_time": 664,
      "service_time": 10
    },
    {
      "id": 42,
      "x": 55,
      "y": 80,
      "demand": 10,
      "ready_time": 33,
      "due_time": 624,
      "service_time": 10
    },
    {
      "id": 43,
      "x": 55,
      "y": 85,
      "demand": 20,
      "ready_time": 549,
      "due_time": 718,
      "service_time": 10
    },
    {
      "id": 44,
      "x": 55,
      "y": 82,
      "demand": 10,
      "ready_time": 62,
      "due_time": 491,
      "service_time": 10
    },
    {
      "id": 45,
      "x": 20,
      "y": 82,
      "demand": 10,
      "ready_time": 37,
      "due_time": 677,
      "service_time": 10
    },
    {
      "id": 46,
      "x": 18,
      "y": 80,
      "demand": 10,
      "ready_time": 435,
      "due_time": 662,
      "service_time": 10
    },
    {
      "id": 47,
      "x": 2,
      "y": 45,
      "demand": 10,
      "ready_time": 38,
      "due_time": 366,
      "service_time": 10
    },
    {
      "id": 48,
      "x": 42,
      "y": 5,
      "demand": 10,
      "ready_time": 636,
      "due_time": 904,
      "service_time": 10
    },
    {
      "id": 49,
      "x": 42,
      "y": 12,
      "demand": 10,
      "ready_time": 423,
      "due_time": 576,
      "service_time": 10
    },
    {
      "id": 50,
      "x": 72,
      "y": 35,
      "demand": 30,
      "ready_time": 471,
      "due_time": 662,
      "service_time": 10
    }
  ]
}